pillow_avif_plugin-1.5.2.dist-info/zip-safe
pillow_avif_plugin-1.5.2.dist-info/RECORD
pillow_avif_plugin-1.5.2.dist-info/LICENSE
pillow_avif_plugin-1.5.2.dist-info/WHEEL
pillow_avif_plugin-1.5.2.dist-info/top_level.txt
pillow_avif_plugin-1.5.2.dist-info/METADATA
pillow_avif/AvifImagePlugin.py
pillow_avif/_avif.cpython-38-darwin.so
pillow_avif/__init__.py
pillow_avif/.dylibs/libavif.16.2.1.dylib
